{
    "userForms": [
        {
            "id": 1,
            "name": "UserForm1",
            "visible": true,
            "autoSize": false,
            "controls":[],
            "style":{},
            "backColor": "Window Text",
            "borderColor": "Button Text",
            "borderStyle":"0 - fmBorderStyleSingle",
            "caption": "UserForm1",
            "cycle": "0 - fmCycleAllForms",
            "drawBuffer": 32000,
            "enabled": true,
            "font": "Tahoma",
            "foreColor": "Button Text",
            "height": 180,
            "helpContextId": 0,
            "keepScrollsBarsVisible": "fmScrollBarsNone",
            "left": 0,
            "mouseIcon": "(None)",
            "mousePointer": "0 - fmMousePointerDefault",
            "picture": "(None)",
            "pictureAlignment": "0 - fmPictureAlignmentTopLeft",
            "pictureSizeMode": "0 - fmPictureSizeModeClip",
            "pictureTiling": false,
            "rightToLeft": false,
            "scrollBars": "0 - fmScrollBarsNone",
            "scrollHeight": 0,
            "scrollLeft": 0,
            "scrollTop": 0,
            "scrollWidth": 0,
            "showModal": true,
            "specialEffect": "0 - fmSpecialEffectFlat",
            "startUpPosition": "0 - Manual",
            "tag": "",
            "top": 0,
            "whatsThisButton": false,
            "whatsThisHelp": false,
            "width": 240,
            "zoom": 100
        }
    ]
}